{
"type": "FeatureCollection",
"crs": { "type": "name", "properties": { "name": "urn:ogc:def:crs:OGC:1.3:CRS84" } },
"features": [
{ "type": "Feature", "properties": { "F1": "Start/Finish", "latitude": 44.436634, "longidute": -121.938929 }, "geometry": { "type": "Point", "coordinates": [ -121.557905999882834, 44.293685999997365 ] } }
]
}
